vyper/VERSION
vyper/__init__.py
vyper/constants.py
vyper/errors.py
vyper/remote.py
vyper/util.py
vyper/vyper.py
vyper/watch.py
vyper_config-1.2.1.dist-info/LICENSE
vyper_config-1.2.1.dist-info/METADATA
vyper_config-1.2.1.dist-info/WHEEL
vyper_config-1.2.1.dist-info/top_level.txt
vyper_config-1.2.1.dist-info/RECORD
