Metadata-Version: 2.1
Name: vyper-config
Version: 1.2.1
Summary: Python configuration with (more) fangs
Home-page: https://github.com/alexferl/vyper
Author: Alexandre Ferland
Author-email: me@alexferl.com
License: MIT
Classifier: Intended Audience :: Developers
Classifier: License :: OSI Approved :: MIT License
Classifier: Operating System :: OS Independent
Classifier: Programming Language :: Python :: 3.8
Classifier: Programming Language :: Python :: 3.9
Classifier: Programming Language :: Python :: 3.10
Classifier: Programming Language :: Python :: 3.11
Classifier: Topic :: Software Development :: Libraries :: Python Modules
Requires-Python: >=3.8
License-File: LICENSE
Requires-Dist: distconfig3 >=1.0.1
Requires-Dist: toml >=0.10.0
Requires-Dist: PyYAML >=6.0.1
Requires-Dist: watchdog >=3.0.0
